demo.py
setup.py
adaptive_interpolation/__init__.py
adaptive_interpolation/adapt.py
adaptive_interpolation/adaptive_interpolation.py
adaptive_interpolation/approximator.py
adaptive_interpolation/generate.py
adaptive_interpolation.egg-info/PKG-INFO
adaptive_interpolation.egg-info/SOURCES.txt
adaptive_interpolation.egg-info/dependency_links.txt
adaptive_interpolation.egg-info/requires.txt
adaptive_interpolation.egg-info/top_level.txt