Metadata-Version: 1.0
Name: adaptive-interpolation
Version: 0.3
Summary: Used to adaptively interpolate a function      then generates C code to quickly evaluate      the interpolation using pyopencl.
Home-page: https://www.github.com/jdoherty7/Adaptive_Interpolation
Author: John Doherty
Author-email: muons.quarks@gmail.com
License: MIT
Platform: UNKNOWN
